sqlalchemy_sqlitecloud/__init__.py
sqlalchemy_sqlitecloud/base.py
sqlalchemy_sqlitecloud/provision.py
sqlalchemy_sqlitecloud/requirements.py
test/__init__.py
test/conftest.py
test/test_suite.py
sqlalchemy_sqlitecloud-0.1.2.dist-info/METADATA
sqlalchemy_sqlitecloud-0.1.2.dist-info/WHEEL
sqlalchemy_sqlitecloud-0.1.2.dist-info/entry_points.txt
sqlalchemy_sqlitecloud-0.1.2.dist-info/top_level.txt
sqlalchemy_sqlitecloud-0.1.2.dist-info/RECORD
