Metadata-Version: 2.1
Name: sqlalchemy-sqlitecloud
Version: 0.1.2
Summary: SQLAlchemy Dialect for SQLite Cloud.
Home-page: https://github.com/sqlitecloud/sqlitecloud-py
Author: sqlitecloud.io
License: MIT
Keywords: SQLAlchemy SQLite Cloud
Platform: UNKNOWN
Classifier: Development Status :: 3 - Alpha
Classifier: Intended Audience :: Developers
Classifier: License :: OSI Approved :: MIT License
Classifier: Programming Language :: Python :: 3.6
Classifier: Programming Language :: Python :: 3.7
Classifier: Programming Language :: Python :: 3.8
Classifier: Programming Language :: Python :: 3.9
Classifier: Programming Language :: Python :: 3.10
Classifier: Programming Language :: Python :: 3.11
Classifier: Programming Language :: Python :: 3.12
Requires-Dist: sqlitecloud (>=0.0.83)
